excel2json_gui/__init__.py
excel2json_gui/excel_converter.py
excel2json_gui/gui.py
excel2json_gui/images/bool.png
excel2json_gui/images/convert-big.png
excel2json_gui/images/convert.png
excel2json_gui/images/dict.png
excel2json_gui/images/folder-open-big.png
excel2json_gui/images/folder-open.png
excel2json_gui/images/icon.ico
excel2json_gui/images/icon.png
excel2json_gui/images/int.png
excel2json_gui/images/list.png
excel2json_gui/images/save-big.png
excel2json_gui/images/str.png
excel2json_gui/main.py
excel2json_gui-0.1.8.dist-info/entry_points.txt
excel2json_gui-0.1.8.dist-info/WHEEL
excel2json_gui-0.1.8.dist-info/METADATA
excel2json_gui-0.1.8.dist-info/RECORD
